fig/drag-upload.png
fig/homepage.png
fig/multilang-preview.png
fig/preview.png
litheserver/__init__.py
litheserver/__main__.py
litheserver/server.py
litheserver-0.1.1.dist-info/licenses/LICENSE
litheserver-0.1.1.dist-info/METADATA
litheserver-0.1.1.dist-info/WHEEL
litheserver-0.1.1.dist-info/entry_points.txt
litheserver-0.1.1.dist-info/top_level.txt
litheserver-0.1.1.dist-info/RECORD
