Metadata-Version: 2.4
Name: litheserver
Version: 0.1.1
Summary: A lightweight local file server with a beautiful web interface
Home-page: https://github.com/xyanmi/litheserver
Author: xyanmi
Author-email: xyanmi <youryanmi@gmail.com>
License: MIT
Project-URL: Homepage, https://github.com/xyanmi/litheserver
Project-URL: Bug Reports, https://github.com/xyanmi/litheserver/issues
Project-URL: Source, https://github.com/xyanmi/litheserver
Keywords: file server,http server,web interface,file sharing,local server,lightweight
Classifier: Development Status :: 4 - Beta
Classifier: Intended Audience :: Developers
Classifier: License :: OSI Approved :: MIT License
Classifier: Operating System :: OS Independent
Classifier: Programming Language :: Python :: 3
Classifier: Programming Language :: Python :: 3.6
Classifier: Programming Language :: Python :: 3.7
Classifier: Programming Language :: Python :: 3.8
Classifier: Programming Language :: Python :: 3.9
Classifier: Programming Language :: Python :: 3.10
Classifier: Programming Language :: Python :: 3.11
Classifier: Programming Language :: Python :: 3.12
Classifier: Topic :: Internet :: WWW/HTTP :: HTTP Servers
Classifier: Topic :: System :: Filesystems
Requires-Python: >=3.6
License-File: LICENSE
Dynamic: author
Dynamic: home-page
Dynamic: license-file
Dynamic: requires-python
